flash_ansr/__init__.py
flash_ansr/__main__.py
flash_ansr/flash_ansr.py
flash_ansr/refine.py
flash_ansr/results.py
flash_ansr/baselines/__init__.py
flash_ansr/baselines/brute_force_model.py
flash_ansr/baselines/skeleton_pool_model.py
flash_ansr/benchmarks/__init__.py
flash_ansr/benchmarks/fastsrb.py
flash_ansr/compat/__init__.py
flash_ansr/compat/convert_data.py
flash_ansr/compat/evaluation_nesymres.py
flash_ansr/compat/evaluation_pysr.py
flash_ansr/compat/nesymres.py
flash_ansr/data/__init__.py
flash_ansr/data/collate.py
flash_ansr/data/data.py
flash_ansr/data/streaming.py
flash_ansr/decoding/mcts.py
flash_ansr/eval/__init__.py
flash_ansr/eval/core.py
flash_ansr/eval/data_sources.py
flash_ansr/eval/engine.py
flash_ansr/eval/evaluation.py
flash_ansr/eval/evaluation_fastsrb.py
flash_ansr/eval/model_adapters.py
flash_ansr/eval/result_store.py
flash_ansr/eval/run_config.py
flash_ansr/eval/sample_metadata.py
flash_ansr/eval/metrics/__init__.py
flash_ansr/eval/metrics/bootstrap.py
flash_ansr/eval/metrics/token_prediction.py
flash_ansr/eval/metrics/zss.py
flash_ansr/expressions/__init__.py
flash_ansr/expressions/compilation.py
flash_ansr/expressions/distributions.py
flash_ansr/expressions/holdout.py
flash_ansr/expressions/normalization.py
flash_ansr/expressions/prior_factory.py
flash_ansr/expressions/skeleton_pool.py
flash_ansr/expressions/skeleton_sampling.py
flash_ansr/expressions/structure.py
flash_ansr/expressions/support_sampling.py
flash_ansr/expressions/token_ops.py
flash_ansr/generation/__init__.py
flash_ansr/generation/beam.py
flash_ansr/generation/mcts.py
flash_ansr/model/__init__.py
flash_ansr/model/factory.py
flash_ansr/model/flash_ansr_model.py
flash_ansr/model/manage.py
flash_ansr/model/pre_encoder.py
flash_ansr/model/tokenizer.py
flash_ansr/model/common/__init__.py
flash_ansr/model/common/components.py
flash_ansr/model/decoders/__init__.py
flash_ansr/model/decoders/components.py
flash_ansr/model/decoders/transformer.py
flash_ansr/model/encoders/__init__.py
flash_ansr-0.4.5.dist-info/licenses/LICENSE
flash_ansr-0.4.5.dist-info/METADATA
flash_ansr-0.4.5.dist-info/WHEEL
flash_ansr-0.4.5.dist-info/entry_points.txt
flash_ansr-0.4.5.dist-info/top_level.txt
flash_ansr-0.4.5.dist-info/RECORD
