Metadata-Version: 2.4
Name: flash_ansr
Version: 0.4.5
Summary: Flash-ANSR: Fast Amortized Neural Symbolic Regression - Discover symbolic expressions from tabular data using SetTransformer and Transformer architectures
Author: Paul Saegert
License-Expression: MIT
Project-URL: Homepage, https://github.com/psaegert/flash-ansr
Project-URL: Documentation, https://flash-ansr.readthedocs.io/en/latest/
Project-URL: Repository, https://github.com/psaegert/flash-ansr
Project-URL: Issues, https://github.com/psaegert/flash-ansr/issues
Project-URL: PyPI, https://pypi.org/project/flash-ansr/
Project-URL: Bug Reports, https://github.com/psaegert/flash-ansr/issues
Project-URL: Demo Notebook, https://github.com/psaegert/flash-ansr/blob/main/experimental/demo.ipynb
Keywords: symbolic-regression,neural-symbolic-regression,simulation-based-inference,transformer,set-transformer,machine-learning,pytorch,expression-discovery,equation-discovery,tabular-data,mathematical-modeling
Classifier: Development Status :: 4 - Beta
Classifier: Intended Audience :: Science/Research
Classifier: Intended Audience :: Developers
Classifier: Topic :: Scientific/Engineering :: Artificial Intelligence
Classifier: Topic :: Scientific/Engineering :: Mathematics
Classifier: Topic :: Software Development :: Libraries :: Python Modules
Classifier: Programming Language :: Python :: 3
Classifier: Programming Language :: Python :: 3.12
Classifier: Operating System :: OS Independent
Requires-Python: >=3.12
License-File: LICENSE
Requires-Dist: absl-py
Requires-Dist: datasets
Requires-Dist: drawdata
Requires-Dist: editdistance
Requires-Dist: einops
Requires-Dist: matplotlib
Requires-Dist: numpy
Requires-Dist: pyyaml
Requires-Dist: schedulefree
Requires-Dist: scikit-learn
Requires-Dist: scipy
Requires-Dist: simplipy
Requires-Dist: torch
Requires-Dist: torch_optimizer
Requires-Dist: tqdm
Requires-Dist: wandb
Requires-Dist: zss
Provides-Extra: dev
Requires-Dist: pre-commit; extra == "dev"
Requires-Dist: pytest; extra == "dev"
Requires-Dist: pytest-cov; extra == "dev"
Requires-Dist: mypy; extra == "dev"
Requires-Dist: flake8; extra == "dev"
Requires-Dist: pygount; extra == "dev"
Requires-Dist: pylint; extra == "dev"
Requires-Dist: types-setuptools; extra == "dev"
Requires-Dist: types-tqdm; extra == "dev"
Requires-Dist: types-toml; extra == "dev"
Requires-Dist: types-PyYAML; extra == "dev"
Requires-Dist: radon; extra == "dev"
Requires-Dist: mkdocs; extra == "dev"
Requires-Dist: mkdocs-material; extra == "dev"
Requires-Dist: mkdocs-autorefs; extra == "dev"
Requires-Dist: mkdocstrings; extra == "dev"
Requires-Dist: mkdocs-get-deps; extra == "dev"
Requires-Dist: mkdocs-material-extensions; extra == "dev"
Requires-Dist: mkdocstrings-python; extra == "dev"
Dynamic: license-file
